MANIFEST.in
README.md
setup.cfg
setup.py
cli/__init__.py
cli/application.py
cli/configuration.py
dcron_cli.egg-info/PKG-INFO
dcron_cli.egg-info/SOURCES.txt
dcron_cli.egg-info/dependency_links.txt
dcron_cli.egg-info/entry_points.txt
dcron_cli.egg-info/requires.txt
dcron_cli.egg-info/top_level.txt